<?xml version="1.0" encoding="UTF-8"?>
<Entities
 universal="password">
    <DataShapes>
        <DataShape
         baseDataShape=""
         description=""
         documentationContent=""
         homeMashup=""
         name="IK.ManageBOM.DataShape"
         projectName="IKEA.CVM"
         tags="">
            <avatar></avatar>
            <DesignTimePermissions>
                <Create></Create>
                <Read></Read>
                <Update></Update>
                <Delete></Delete>
                <Metadata></Metadata>
            </DesignTimePermissions>
            <RunTimePermissions></RunTimePermissions>
            <VisibilityPermissions>
                <Visibility></Visibility>
            </VisibilityPermissions>
            <ConfigurationTableDefinitions></ConfigurationTableDefinitions>
            <ConfigurationTables></ConfigurationTables>
            <FieldDefinitions>
                <FieldDefinition
                 aspect.isPrimaryKey="false"
                 baseType="HTML"
                 description=""
                 name="action"
                 ordinal="12"></FieldDefinition>
                <FieldDefinition
                 aspect.isPrimaryKey="false"
                 baseType="STRING"
                 description=""
                 name="article_id"
                 ordinal="15"></FieldDefinition>
                <FieldDefinition
                 aspect.isPrimaryKey="false"
                 baseType="STRING"
                 description=""
                 name="article_name"
                 ordinal="1"></FieldDefinition>
                <FieldDefinition
                 aspect.isPrimaryKey="false"
                 baseType="STRING"
                 description=""
                 name="article_number"
                 ordinal="2"></FieldDefinition>
                <FieldDefinition
                 aspect.isPrimaryKey="false"
                 baseType="HTML"
                 description=""
                 name="association_pending"
                 ordinal="10"></FieldDefinition>
                <FieldDefinition
                 aspect.isPrimaryKey="false"
                 baseType="HTML"
                 description=""
                 name="BOM_part_requirements"
                 ordinal="8"></FieldDefinition>
                <FieldDefinition
                 aspect.isPrimaryKey="false"
                 baseType="STRING"
                 description=""
                 name="compliant_deadline"
                 ordinal="4"></FieldDefinition>
                <FieldDefinition
                 aspect.isPrimaryKey="false"
                 baseType="HTML"
                 description=""
                 name="connected_supply_actors"
                 ordinal="3"></FieldDefinition>
                <FieldDefinition
                 aspect.isPrimaryKey="false"
                 baseType="HTML"
                 description=""
                 name="Material"
                 ordinal="7"></FieldDefinition>
                <FieldDefinition
                 aspect.isPrimaryKey="false"
                 baseType="STRING"
                 description=""
                 name="part_number"
                 ordinal="13"></FieldDefinition>
                <FieldDefinition
                 aspect.isPrimaryKey="false"
                 baseType="HTML"
                 description=""
                 name="Parts"
                 ordinal="6"></FieldDefinition>
                <FieldDefinition
                 aspect.isPrimaryKey="false"
                 baseType="STRING"
                 description=""
                 name="production_deadline"
                 ordinal="5"></FieldDefinition>
                <FieldDefinition
                 aspect.isPrimaryKey="false"
                 baseType="HTML"
                 description=""
                 name="requirement_pending"
                 ordinal="9"></FieldDefinition>
                <FieldDefinition
                 aspect.isPrimaryKey="false"
                 baseType="STRING"
                 description=""
                 name="status"
                 ordinal="11"></FieldDefinition>
                <FieldDefinition
                 aspect.isPrimaryKey="false"
                 baseType="INFOTABLE"
                 description=""
                 name="taskDetails"
                 ordinal="14"></FieldDefinition>
            </FieldDefinitions>
        </DataShape>
    </DataShapes>
</Entities>
