<?xml version="1.0" encoding="UTF-8"?>
<Entities
 universal="password">
    <DataShapes>
        <DataShape
         baseDataShape=""
         description=""
         documentationContent=""
         homeMashup=""
         name="IK.PlantDeclaration.DataShape"
         projectName="IKEA.CVM"
         tags="">
            <avatar></avatar>
            <DesignTimePermissions>
                <Create></Create>
                <Read></Read>
                <Update></Update>
                <Delete></Delete>
                <Metadata></Metadata>
            </DesignTimePermissions>
            <RunTimePermissions></RunTimePermissions>
            <VisibilityPermissions>
                <Visibility></Visibility>
            </VisibilityPermissions>
            <ConfigurationTableDefinitions></ConfigurationTableDefinitions>
            <ConfigurationTables></ConfigurationTables>
            <FieldDefinitions>
                <FieldDefinition
                 aspect.isPrimaryKey="false"
                 baseType="STRING"
                 description=""
                 name="comment"
                 ordinal="6"></FieldDefinition>
                <FieldDefinition
                 aspect.isPrimaryKey="false"
                 baseType="DATETIME"
                 description=""
                 name="last_modified"
                 ordinal="5"></FieldDefinition>
                <FieldDefinition
                 aspect.dataShape="IK.PlantReportData.DataShape"
                 aspect.isPrimaryKey="false"
                 baseType="INFOTABLE"
                 description=""
                 name="plant_report"
                 ordinal="4"></FieldDefinition>
                <FieldDefinition
                 aspect.isPrimaryKey="false"
                 baseType="STRING"
                 description=""
                 name="recycle_percentage"
                 ordinal="1"></FieldDefinition>
                <FieldDefinition
                 aspect.isPrimaryKey="false"
                 baseType="DATETIME"
                 description=""
                 name="valid_from"
                 ordinal="2"></FieldDefinition>
                <FieldDefinition
                 aspect.isPrimaryKey="false"
                 baseType="DATETIME"
                 description=""
                 name="valid_to"
                 ordinal="3"></FieldDefinition>
            </FieldDefinitions>
        </DataShape>
    </DataShapes>
</Entities>
