<?xml version="1.0" encoding="UTF-8"?>
<Entities
 universal="password">
    <DataShapes>
        <DataShape
         baseDataShape=""
         description=""
         documentationContent=""
         homeMashup=""
         name="IK.SupplyChainTier.DataShape"
         projectName="IKEA.CVM"
         tags="">
            <avatar></avatar>
            <DesignTimePermissions>
                <Create></Create>
                <Read></Read>
                <Update></Update>
                <Delete></Delete>
                <Metadata></Metadata>
            </DesignTimePermissions>
            <RunTimePermissions></RunTimePermissions>
            <VisibilityPermissions>
                <Visibility></Visibility>
            </VisibilityPermissions>
            <ConfigurationTableDefinitions></ConfigurationTableDefinitions>
            <ConfigurationTables></ConfigurationTables>
            <FieldDefinitions>
                <FieldDefinition
                 aspect.isPrimaryKey="false"
                 baseType="HTML"
                 description=""
                 name="action"
                 ordinal="6"></FieldDefinition>
                <FieldDefinition
                 aspect.isPrimaryKey="false"
                 baseType="STRING"
                 description=""
                 name="id"
                 ordinal="2"></FieldDefinition>
                <FieldDefinition
                 aspect.isPrimaryKey="false"
                 baseType="STRING"
                 description=""
                 name="legal_name"
                 ordinal="5"></FieldDefinition>
                <FieldDefinition
                 aspect.isPrimaryKey="false"
                 baseType="STRING"
                 description=""
                 name="supply_object_name"
                 ordinal="3"></FieldDefinition>
                <FieldDefinition
                 aspect.isPrimaryKey="false"
                 baseType="INTEGER"
                 description=""
                 name="tier"
                 ordinal="4"></FieldDefinition>
                <FieldDefinition
                 aspect.isPrimaryKey="false"
                 baseType="STRING"
                 description=""
                 name="unique_id"
                 ordinal="1"></FieldDefinition>
            </FieldDefinitions>
        </DataShape>
    </DataShapes>
</Entities>
