<?xml version="1.0" encoding="UTF-8"?>
<Entities
 universal="password">
    <DataShapes>
        <DataShape
         baseDataShape=""
         description=""
         documentationContent=""
         homeMashup=""
         name="IK.SupplyObject.DataShape"
         projectName="IKEA.CVM"
         tags="">
            <avatar></avatar>
            <DesignTimePermissions>
                <Create></Create>
                <Read></Read>
                <Update></Update>
                <Delete></Delete>
                <Metadata></Metadata>
            </DesignTimePermissions>
            <RunTimePermissions></RunTimePermissions>
            <VisibilityPermissions>
                <Visibility></Visibility>
            </VisibilityPermissions>
            <ConfigurationTableDefinitions></ConfigurationTableDefinitions>
            <ConfigurationTables></ConfigurationTables>
            <FieldDefinitions>
                <FieldDefinition
                 aspect.isPrimaryKey="false"
                 baseType="HTML"
                 description=""
                 name="action"
                 ordinal="10"></FieldDefinition>
                <FieldDefinition
                 aspect.isPrimaryKey="false"
                 baseType="STRING"
                 description=""
                 name="actor_type"
                 ordinal="11"></FieldDefinition>
                <FieldDefinition
                 aspect.isPrimaryKey="false"
                 baseType="STRING"
                 description=""
                 name="address"
                 ordinal="15"></FieldDefinition>
                <FieldDefinition
                 aspect.isPrimaryKey="false"
                 baseType="INTEGER"
                 description=""
                 name="connected_articles"
                 ordinal="26"></FieldDefinition>
                <FieldDefinition
                 aspect.isPrimaryKey="false"
                 baseType="HTML"
                 description=""
                 name="connected_articles_html"
                 ordinal="27"></FieldDefinition>
                <FieldDefinition
                 aspect.isPrimaryKey="false"
                 baseType="STRING"
                 description=""
                 name="connected_boms"
                 ordinal="9"></FieldDefinition>
                <FieldDefinition
                 aspect.isPrimaryKey="false"
                 baseType="STRING"
                 description=""
                 name="connected_supply_chain"
                 ordinal="8"></FieldDefinition>
                <FieldDefinition
                 aspect.isPrimaryKey="false"
                 baseType="STRING"
                 description=""
                 name="country"
                 ordinal="5"></FieldDefinition>
                <FieldDefinition
                 aspect.isPrimaryKey="false"
                 baseType="HTML"
                 description=""
                 name="display_name"
                 ordinal="24"></FieldDefinition>
                <FieldDefinition
                 aspect.isPrimaryKey="false"
                 baseType="STRING"
                 description=""
                 name="duns_number"
                 ordinal="14"></FieldDefinition>
                <FieldDefinition
                 aspect.isPrimaryKey="false"
                 baseType="STRING"
                 description=""
                 name="gln_code"
                 ordinal="18"></FieldDefinition>
                <FieldDefinition
                 aspect.isPrimaryKey="false"
                 baseType="BOOLEAN"
                 description=""
                 name="is_selected"
                 ordinal="28"></FieldDefinition>
                <FieldDefinition
                 aspect.isPrimaryKey="false"
                 baseType="DATETIME"
                 description=""
                 name="last_modified"
                 ordinal="30"></FieldDefinition>
                <FieldDefinition
                 aspect.isPrimaryKey="false"
                 baseType="STRING"
                 description=""
                 name="latitude"
                 ordinal="16"></FieldDefinition>
                <FieldDefinition
                 aspect.isPrimaryKey="false"
                 baseType="STRING"
                 description=""
                 name="legal_code"
                 ordinal="19"></FieldDefinition>
                <FieldDefinition
                 aspect.isPrimaryKey="false"
                 baseType="STRING"
                 description=""
                 name="legal_name"
                 ordinal="13"></FieldDefinition>
                <FieldDefinition
                 aspect.isPrimaryKey="false"
                 baseType="STRING"
                 description=""
                 name="longtitude"
                 ordinal="17"></FieldDefinition>
                <FieldDefinition
                 aspect.isPrimaryKey="false"
                 baseType="STRING"
                 description=""
                 name="material_sub_type"
                 ordinal="25"></FieldDefinition>
                <FieldDefinition
                 aspect.isPrimaryKey="false"
                 baseType="STRING"
                 description=""
                 name="name"
                 ordinal="1"></FieldDefinition>
                <FieldDefinition
                 aspect.isPrimaryKey="false"
                 baseType="STRING"
                 description=""
                 name="object_type"
                 ordinal="3"></FieldDefinition>
                <FieldDefinition
                 aspect.dataShape="GenericStringList"
                 aspect.isPrimaryKey="false"
                 baseType="INFOTABLE"
                 description=""
                 name="productionDetails"
                 ordinal="20"></FieldDefinition>
                <FieldDefinition
                 aspect.isPrimaryKey="false"
                 baseType="STRING"
                 description=""
                 name="status"
                 ordinal="22"></FieldDefinition>
                <FieldDefinition
                 aspect.isPrimaryKey="false"
                 baseType="NUMBER"
                 description=""
                 name="supplier_id"
                 ordinal="31"></FieldDefinition>
                <FieldDefinition
                 aspect.isPrimaryKey="false"
                 baseType="STRING"
                 description=""
                 name="supply_chain_actor"
                 ordinal="4"></FieldDefinition>
                <FieldDefinition
                 aspect.isPrimaryKey="false"
                 baseType="STRING"
                 description=""
                 name="supply_object_id"
                 ordinal="6"></FieldDefinition>
                <FieldDefinition
                 aspect.isPrimaryKey="false"
                 baseType="STRING"
                 description=""
                 name="supply_object_oid"
                 ordinal="23"></FieldDefinition>
                <FieldDefinition
                 aspect.isPrimaryKey="false"
                 baseType="STRING"
                 description=""
                 name="trade_good_id"
                 ordinal="21"></FieldDefinition>
                <FieldDefinition
                 aspect.isPrimaryKey="false"
                 baseType="STRING"
                 description=""
                 name="type"
                 ordinal="2"></FieldDefinition>
                <FieldDefinition
                 aspect.isPrimaryKey="false"
                 baseType="STRING"
                 description=""
                 name="type_of_operation"
                 ordinal="12"></FieldDefinition>
                <FieldDefinition
                 aspect.isPrimaryKey="false"
                 baseType="STRING"
                 description=""
                 name="version"
                 ordinal="7"></FieldDefinition>
            </FieldDefinitions>
        </DataShape>
    </DataShapes>
</Entities>
